apt_search/__init__.py
apt_search/__main__.py
apt_search/main.py
apt_search-0.1.3.dist-info/METADATA
apt_search-0.1.3.dist-info/LICENSE
apt_search-0.1.3.dist-info/WHEEL
apt_search-0.1.3.dist-info/entry_points.txt
apt_search-0.1.3.dist-info/RECORD
