Metadata-Version: 2.1
Name: apt-search
Version: 0.1.3
Summary: Search Ubuntu packages.
Home-page: https://github.com/DavidHeresy/apt-search
License: MIT
Author: David Härer
Author-email: david@familie-haerer.de
Requires-Python: >=3.10,<4.0
Classifier: License :: OSI Approved :: MIT License
Classifier: Programming Language :: Python :: 3
Classifier: Programming Language :: Python :: 3.10
Classifier: Programming Language :: Python :: 3.11
Requires-Dist: beautifulsoup4 (>=4.11.1,<5.0.0)
Requires-Dist: httpx (>=0.23.3,<0.24.0)
Requires-Dist: typer (>=0.7.0,<0.8.0)
